kenobi.py
kenobi-4.0.dist-info/LICENSE
kenobi-4.0.dist-info/METADATA
kenobi-4.0.dist-info/WHEEL
kenobi-4.0.dist-info/top_level.txt
kenobi-4.0.dist-info/RECORD
