Metadata-Version: 2.1
Name: kenobi
Version: 4.0
Summary: document based database using sqlite
Home-page: http://patx.github.io/kenobi
Author: Harrison Erd
Author-email: harrisonerd@gmail.com
License: three-clause BSD
Classifier: Programming Language :: Python
Classifier: License :: OSI Approved :: BSD License
Classifier: Intended Audience :: Developers
Classifier: Topic :: Database
License-File: LICENSE
